Metadata-Version: 2.1
Name: python-switchbot-v2
Version: 2.3.1
Summary: A Python library to control SwitchBot devices connected to SwitchBot Hub.
Home-page: https://github.com/areazus/python-switchbot-v2
Author: Ahmed Reaz
Author-email: dev@areaz.us
License: MIT
Keywords: python-switchbot-v2
Classifier: Development Status :: 4 - Beta
Classifier: License :: OSI Approved :: MIT License
Classifier: Programming Language :: Python :: 3
Classifier: Programming Language :: Python :: 3 :: Only
Classifier: Topic :: Home Automation
Requires-Python: >=3.7
License-File: LICENSE
Requires-Dist: requests
Requires-Dist: pyhumps
